locate_pixelcolor/LICENSE
locate_pixelcolor/README.MD
locate_pixelcolor/__init__.py
locate_pixelcolor/requirements.txt
locate_pixelcolor/thirdparty.json
locate_pixelcolor-0.10.dist-info/LICENSE.rst
locate_pixelcolor-0.10.dist-info/METADATA
locate_pixelcolor-0.10.dist-info/WHEEL
locate_pixelcolor-0.10.dist-info/top_level.txt
locate_pixelcolor-0.10.dist-info/RECORD
